odoo/addons/repair_purchase_return/README.rst
odoo/addons/repair_purchase_return/__init__.py
odoo/addons/repair_purchase_return/__manifest__.py
odoo/addons/repair_purchase_return/i18n/it.po
odoo/addons/repair_purchase_return/i18n/repair_purchase_return.pot
odoo/addons/repair_purchase_return/models/__init__.py
odoo/addons/repair_purchase_return/models/purchase_return_order.py
odoo/addons/repair_purchase_return/models/purchase_return_order_line.py
odoo/addons/repair_purchase_return/models/repair_fee.py
odoo/addons/repair_purchase_return/models/repair_line.py
odoo/addons/repair_purchase_return/models/repair_order.py
odoo/addons/repair_purchase_return/readme/CONTRIBUTORS.rst
odoo/addons/repair_purchase_return/readme/DESCRIPTION.rst
odoo/addons/repair_purchase_return/readme/USAGE.rst
odoo/addons/repair_purchase_return/security/ir.model.access.csv
odoo/addons/repair_purchase_return/static/description/icon.png
odoo/addons/repair_purchase_return/static/description/index.html
odoo/addons/repair_purchase_return/tests/__init__.py
odoo/addons/repair_purchase_return/tests/test_repair_purchase_return_order.py
odoo/addons/repair_purchase_return/views/purchase_return_order_views.xml
odoo/addons/repair_purchase_return/views/repair_order_views.xml
odoo/addons/repair_purchase_return/wizards/__init__.py
odoo/addons/repair_purchase_return/wizards/repair_purchase_return_wiz.py
odoo/addons/repair_purchase_return/wizards/repair_purchase_return_wiz_views.xml
odoo_addon_repair_purchase_return-16.0.1.0.1.dist-info/METADATA
odoo_addon_repair_purchase_return-16.0.1.0.1.dist-info/WHEEL
odoo_addon_repair_purchase_return-16.0.1.0.1.dist-info/top_level.txt
odoo_addon_repair_purchase_return-16.0.1.0.1.dist-info/RECORD
